nnd/.gitignore
nnd/__init__.py
nnd/logger.py
nnd/models/__init__.py
nnd/models/models_pipeline.py
nnd/models/nnUNet/__init__.py
nnd/models/nnUNet/nnUNet_pipeline.py
nnd/models/nnUNet/config/dataset.json
nnd/models/nnUNet/config/splits_final.json
nnd/utils/__init__.py
nnd/utils/utils_dataset.py
nnd/utils/utils_visualization.py
nnd-0.2.0.dist-info/METADATA
nnd-0.2.0.dist-info/WHEEL
nnd-0.2.0.dist-info/licenses/LICENSE.md
nnd-0.2.0.dist-info/RECORD
