Metadata-Version: 2.4
Name: nnd
Version: 0.2.0
Summary: Python library designed to analyze and detect the sclerosis from MRI brain scans using advanced deep learning algorithms
Author-email: Emilio Rodrigo Carreira Villalta <emiliorodrigo.ecr@gmail.com>
Maintainer-email: Emilio Rodrigo Carreira Villalta <emiliorodrigo.ecr@gmail.com>
License-File: LICENSE.md
Classifier: Development Status :: 5 - Production/Stable
Classifier: Intended Audience :: Science/Research
Classifier: License :: Other/Proprietary License
Classifier: Programming Language :: Python :: 3.10
Classifier: Topic :: Scientific/Engineering :: Artificial Intelligence
Requires-Python: >=3.10
Requires-Dist: coverage==7.6.8
Requires-Dist: emoji==2.12.1
Requires-Dist: gdown==5.2.0
Requires-Dist: ipympl==0.9.4
Requires-Dist: ipython==8.30.0
Requires-Dist: ipywidgets==8.1.5
Requires-Dist: jupyterlab==4.2.5
Requires-Dist: matplotlib==3.9.2
Requires-Dist: nibabel==5.2.1
Requires-Dist: nnunetv2==2.3.1
Requires-Dist: opencv-contrib-python==4.10.0.84
Requires-Dist: opencv-python==4.10.0.84
Requires-Dist: pycocotools==2.0.8
Requires-Dist: ruff==0.6.9
Requires-Dist: saes==1.3.6
Requires-Dist: scikit-image==0.24.0
Requires-Dist: scipy==1.14.1
Requires-Dist: sphinx-rtd-theme==3.0.2
Requires-Dist: sphinx==8.1.3
Requires-Dist: torch>=2.7.0
Requires-Dist: torchaudio
Requires-Dist: torchvision
Requires-Dist: ultralytics==8.3.7
Requires-Dist: vedo==2025.5.3
